pytest_rotest.py
pytest_rotest-0.1.0.dist-info/LICENSE
pytest_rotest-0.1.0.dist-info/METADATA
pytest_rotest-0.1.0.dist-info/WHEEL
pytest_rotest-0.1.0.dist-info/entry_points.txt
pytest_rotest-0.1.0.dist-info/top_level.txt
pytest_rotest-0.1.0.dist-info/RECORD
