Metadata-Version: 2.1
Name: pytest-rotest
Version: 0.1.0
Summary: Pytest integration with rotest
Home-page: https://github.com/UnDarkle/pytest-rotest
Author-email: gregoil@walla.co.il
Maintainer-email: gregoil@walla.co.il
License: MIT
Platform: UNKNOWN
Classifier: Framework :: Pytest
Classifier: Intended Audience :: Developers
Classifier: Topic :: Software Development :: Testing
Classifier: Programming Language :: Python
Classifier: Programming Language :: Python :: 2
Classifier: Programming Language :: Python :: 2.7
Classifier: Programming Language :: Python :: 3
Classifier: Programming Language :: Python :: 3.6
Classifier: Programming Language :: Python :: 3.7
Classifier: Programming Language :: Python :: Implementation :: CPython
Classifier: Operating System :: OS Independent
Classifier: License :: OSI Approved :: MIT License
Requires-Python: >=2.7, !=3.0.*, !=3.1.*, !=3.2.*, !=3.3.*, !=3.4.*, !=3.5.*
Requires-Dist: pytest (>=3.5.0)
Requires-Dist: rotest (>=7.3.0)
